getlino/__init__.py
getlino/cli.py
getlino/configure.py
getlino/list.py
getlino/startproject.py
getlino/startsite.py
getlino/utils.py
getlino/templates/apache.conf
getlino/templates/asgi.py
getlino/templates/daphne_supervisor.conf
getlino/templates/django_settings.py
getlino/templates/healthcheck.sh
getlino/templates/lino.ini
getlino/templates/make_snapshot.sh
getlino/templates/manage.py
getlino/templates/nginx.conf
getlino/templates/nginx_asgi.conf
getlino/templates/pull.sh
getlino/templates/reload_services.sh
getlino/templates/settings.py
getlino/templates/uwsgi.ini
getlino/templates/uwsgi_params
getlino/templates/wsgi.py
getlino-25.10.0.dist-info/METADATA
getlino-25.10.0.dist-info/WHEEL
getlino-25.10.0.dist-info/entry_points.txt
getlino-25.10.0.dist-info/licenses/COPYING
getlino-25.10.0.dist-info/RECORD
