Metadata-Version: 2.4
Name: getlino
Version: 25.10.0
Summary: A command-line tool for installing Lino in different environments.
Project-URL: Homepage, https://getlino.lino-framework.org/
Project-URL: Repository, https://gitlab.com/lino-framework/getlino
Author-email: Rumma & Ko Ltd <info@saffre-rumma.net>, Luc Saffre <luc@saffre-rumma.net>
License:                     GNU AFFERO GENERAL PUBLIC LICENSE
License-File: COPYING
Keywords: Django,React,customized,framework
Classifier: Development Status :: 5 - Production/Stable
Classifier: Environment :: Web Environment
Classifier: Framework :: Django
Classifier: Intended Audience :: Developers
Classifier: Intended Audience :: System Administrators
Classifier: License :: OSI Approved :: GNU Affero General Public License v3
Classifier: Natural Language :: English
Classifier: Natural Language :: French
Classifier: Natural Language :: German
Classifier: Operating System :: OS Independent
Classifier: Programming Language :: Python
Classifier: Programming Language :: Python :: 3
Classifier: Topic :: Database :: Front-Ends
Classifier: Topic :: Software Development :: Libraries :: Application Frameworks
Classifier: Topic :: System :: Installation/Setup
Requires-Python: >=3.8
Requires-Dist: click
Requires-Dist: distro
Requires-Dist: gitpython
Requires-Dist: jinja2
Requires-Dist: rstgen
Requires-Dist: synodal
Requires-Dist: virtualenv
Provides-Extra: dev
Requires-Dist: hatch; extra == 'dev'
Requires-Dist: pytest; extra == 'dev'
Requires-Dist: pytest-cov; extra == 'dev'
Provides-Extra: testing
Requires-Dist: atelier; extra == 'testing'
Requires-Dist: pytest; extra == 'testing'
Requires-Dist: pytest-env; extra == 'testing'
Requires-Dist: pytest-forked; extra == 'testing'
Requires-Dist: pytest-html; extra == 'testing'
